README
setup.py
admincsvimport/__init__.py
admincsvimport/models.py
admincsvimport/tests.py
admincsvimport/views.py
admincsvimport.egg-info/PKG-INFO
admincsvimport.egg-info/SOURCES.txt
admincsvimport.egg-info/dependency_links.txt
admincsvimport.egg-info/not-zip-safe
admincsvimport.egg-info/top_level.txt