Metadata-Version: 1.0
Name: admincsvimport
Version: 0.1
Summary: Add loaddata like csv support at Django Admin Site
Home-page: https://github.com/terryh/django-admincsvimport/
Author: Terry Huang
Author-email: terryh.tp@gmail.com
License: UNKNOWN
Platform: UNKNOWN
Classifier: Development Status :: 3 - Alpha
Classifier: Environment :: Web Environment
Classifier: Framework :: Django
Classifier: Intended Audience :: Developers
Classifier: License :: OSI Approved :: BSD License
Classifier: Operating System :: OS Independent
Classifier: Programming Language :: Python
